aesrepeat/__init__.py
aesrepeat/internal/__init__.py
aesrepeat-1.0.0.dist-info/METADATA
aesrepeat-1.0.0.dist-info/WHEEL
aesrepeat-1.0.0.dist-info/top_level.txt
aesrepeat-1.0.0.dist-info/RECORD
